tablerpy
